jawasCalcul/__init__.py
jawasCalcul-0.2.dist-info/LICENSE.TXT
jawasCalcul-0.2.dist-info/METADATA
jawasCalcul-0.2.dist-info/WHEEL
jawasCalcul-0.2.dist-info/top_level.txt
jawasCalcul-0.2.dist-info/RECORD
