Metadata-Version: 2.1
Name: jawasCalcul
Version: 0.2
Summary: nothing
Author: jawa
Author-email: jawahar2k2@gmail.com
Classifier: Programming Language :: Python :: 3
Classifier: License :: OSI Approved :: MIT License
Classifier: Operating System :: OS Independent
License-File: LICENSE.TXT
